{"id":"81BF4FA9-E89D-4B57-887D-52658254E0DD","validationEntity":{"analysedDataType":"auto","dataResult":{"createdDate":"2022-10-30T23:57:49Z"}},"modelEntity":{"createdDate":"2022-10-30T23:57:49Z","id":"F3D3EF05-88FF-4C29-8A31-FF13CC7666B0","experimentID":"81BF4FA9-E89D-4B57-887D-52658254E0DD","title":"","modifiedDate":"2022-10-30T23:57:49Z","preferredFilename":"","version":"1.0","modelURL":"Models\/DimSumClassifier%201.mlmodel"},"version":"1.0","settingEntity":{"taskType":"imageClassifier","augmentations":[],"styleTransferAlgorithmType":"image","iterationCount":25,"transferLearningEmbeddingType":"dynamic","harVideoAugmentations":0,"handPoseClassifierAugmentations":[],"algorithmType":"maxEnt","handActionClassifierAugmentations":[],"seedType":"default","featureNames":[]},"state":"trained","trainingEntity":{"finishTime":"2022-10-30T23:59:27Z","validationResults":{"imageClassifier":{"confusionMatrix":[{"expected":"bakedlavabun","actual":"bakedlavabun","count":2},{"expected":"beefriceroll","actual":"beefriceroll","count":1},{"expected":"chaozhoufunguo","actual":"chaozhoufunguo","count":1},{"expected":"porkshrimpiumai","actual":"chasiubao","count":1},{"expected":"tofupudding","actual":"chasiubao","count":1},{"expected":"chasiufriedrice","actual":"chasiufriedrice","count":1},{"expected":"chinesesausagefriedrice","actual":"chinesesausagefriedrice","count":2},{"expected":"shrimpdumpling","actual":"custardbun","count":1},{"expected":"bakedchasiubao","actual":"deepfrieddumpling","count":1},{"expected":"deepfrieddumpling","actual":"deepfrieddumpling","count":2},{"expected":"shrimpfriedrice","actual":"eggfriedrice","count":1},{"expected":"friedeggtomatonoodlesoup","actual":"friedeggtomatonoodlesoup","count":1},{"expected":"friedshrimp","actual":"friedshrimp","count":1},{"expected":"hkeggtart","actual":"hkeggtart","count":2},{"expected":"hotdogbun","actual":"hotdogbun","count":1},{"expected":"jellyfishsalad","actual":"jellyfishsalad","count":1},{"expected":"malaycake","actual":"malaycake","count":1},{"expected":"portugueseeggtart","actual":"malaycake","count":1},{"expected":"wintermelontea","actual":"mangogreentea","count":1},{"expected":"meatball","actual":"meatball","count":2},{"expected":"bakedchasiubao","actual":"mochi","count":2},{"expected":"pigletbun","actual":"pigletbun","count":2},{"expected":"shrimpsiumai","actual":"porkshrimpiumai","count":1},{"expected":"porksiumai","actual":"porksiumai","count":1},{"expected":"sesameball","actual":"sesameball","count":1},{"expected":"redoilwonton","actual":"shrimpriceroll","count":1},{"expected":"bakedchasiubao","actual":"springroll","count":1},{"expected":"springroll","actual":"springroll","count":1},{"expected":"shrimpdumpling","actual":"stickyricecake","count":1},{"expected":"stuffedeggplant","actual":"stuffedeggplant","count":1},{"expected":"sugarcaneshrimp","actual":"sugarcaneshrimp","count":1},{"expected":"tofupudding","actual":"tofupudding","count":1},{"expected":"wintermelontea","actual":"wintermelontea","count":1}],"statsByLabel":{"shrimpriceroll":{"count":1,"precisionRecall":{"success":{"recall":0,"precision":0}}},"porkshrimpiumai":{"count":1,"precisionRecall":{"success":{"recall":0,"precision":0}}},"friedshrimp":{"count":1,"precisionRecall":{"success":{"recall":1,"precision":1}}},"wintermelontea":{"count":1,"precisionRecall":{"success":{"recall":1,"precision":0.5}}},"mangogreentea":{"count":1,"precisionRecall":{"success":{"recall":0,"precision":0}}},"shrimpdumpling":{"count":0,"precisionRecall":{"success":{"recall":0,"precision":0}}},"portugueseeggtart":{"count":0,"precisionRecall":{"success":{"recall":0,"precision":0}}},"stuffedeggplant":{"count":1,"precisionRecall":{"success":{"recall":1,"precision":1}}},"shrimpsiumai":{"count":0,"precisionRecall":{"success":{"recall":0,"precision":0}}},"chinesesausagefriedrice":{"count":2,"precisionRecall":{"success":{"recall":1,"precision":1}}},"tofupudding":{"count":1,"precisionRecall":{"success":{"recall":1,"precision":0.5}}},"sugarcaneshrimp":{"count":1,"precisionRecall":{"success":{"recall":1,"precision":1}}},"beefriceroll":{"count":1,"precisionRecall":{"success":{"recall":1,"precision":1}}},"chasiubao":{"count":2,"precisionRecall":{"success":{"recall":0,"precision":0}}},"sesameball":{"count":1,"precisionRecall":{"success":{"recall":1,"precision":1}}},"chaozhoufunguo":{"count":1,"precisionRecall":{"success":{"recall":1,"precision":1}}},"custardbun":{"count":1,"precisionRecall":{"success":{"recall":0,"precision":0}}},"chasiufriedrice":{"count":1,"precisionRecall":{"success":{"recall":1,"precision":1}}},"springroll":{"count":2,"precisionRecall":{"success":{"recall":0.5,"precision":1}}},"stickyricecake":{"count":1,"precisionRecall":{"success":{"recall":0,"precision":0}}},"porksiumai":{"count":1,"precisionRecall":{"success":{"recall":1,"precision":1}}},"hkeggtart":{"count":2,"precisionRecall":{"success":{"recall":1,"precision":1}}},"eggfriedrice":{"count":1,"precisionRecall":{"success":{"recall":0,"precision":0}}},"redoilwonton":{"count":0,"precisionRecall":{"success":{"recall":0,"precision":0}}},"mochi":{"count":2,"precisionRecall":{"success":{"recall":0,"precision":0}}},"meatball":{"count":2,"precisionRecall":{"success":{"recall":1,"precision":1}}},"shrimpfriedrice":{"count":0,"precisionRecall":{"success":{"recall":0,"precision":0}}},"hotdogbun":{"count":1,"precisionRecall":{"success":{"recall":1,"precision":1}}},"friedeggtomatonoodlesoup":{"count":1,"precisionRecall":{"success":{"recall":1,"precision":1}}},"bakedchasiubao":{"count":0,"precisionRecall":{"success":{"recall":0,"precision":0}}},"deepfrieddumpling":{"count":3,"precisionRecall":{"success":{"recall":0.66666666666666663,"precision":1}}},"pigletbun":{"count":2,"precisionRecall":{"success":{"recall":1,"precision":1}}},"malaycake":{"count":2,"precisionRecall":{"success":{"recall":0.5,"precision":1}}},"jellyfishsalad":{"count":1,"precisionRecall":{"success":{"recall":1,"precision":1}}},"bakedlavabun":{"count":2,"precisionRecall":{"success":{"recall":1,"precision":1}}}},"accuracy":0.67500000000000004}},"dataURL":"file:\/\/\/Users\/philipchu\/dev\/github\/dimsumml\/train\/","dataResult":{"itemsCount":702,"createdDate":"2022-10-30T23:57:49Z","dataURL":"file:\/\/\/Users\/philipchu\/dev\/github\/dimsumml\/train\/","dataSourceID":"384A0C1F-BB47-4B79-9D3C-A28B7D418D05","classesCount":92,"dataAnalysis":{"summary":{"sampleCount":702,"classCount":92,"canUseValidation":1},"issues":[{"description":"92 classes found, including pigletbun, porkshrimpiumai, shrimpdumpling","severity":"debug"},{"description":"702 images found, automatically creating validation set","severity":"good"},{"description":"Smallest class is \"scallopsiumai\" with 1 images","severity":"debug"},{"description":"Largest class is \"pigletbun\" with 14 images","severity":"debug"}],"classifierAnalysis":{"labelStats":{"friedeggtomatonoodlesoup":6,"malaycake":10,"porksungbun":9,"billionairefriedrice":1,"panfriedriceroll":4,"westlakesoup":10,"chasiupuff":8,"steamedegg":10,"sweetpotatosoup":8,"friedshrimp":10,"porkbelly":9,"tofuskinroll":10,"chasiubao":10,"deepfrieddumpling":9,"mushroomsiumai":3,"redoilwonton":3,"jellyfishsalad":5,"seaweedsalad":5,"tofupudding":9,"friedwonton":10,"pineapplebun":7,"saltandpeppersquid":5,"fishsiumai":2,"friedfishball":8,"sugarcaneshrimp":7,"shrimpsiumai":3,"hklemonicetea":8,"jasminetea":10,"tarodumpling":10,"shrimpdumpling":12,"mochi":4,"hkeggtart":10,"flakyskinbakedchasiubao":10,"currypuff":10,"chinesebroccoli":10,"stuffedtofu":5,"preservedeggporkcongee":10,"vegetablefriedrice":2,"chivedumpling":10,"curryfishball":7,"turnipcake":10,"meatball":10,"vietnamesespringroll":7,"singaporenoodles":10,"portugueseeggtart":10,"saltedfishmincedporkclaypotrice":6,"beefriceroll":9,"mangogreentea":3,"sesameball":10,"chasiufriedrice":8,"oolongtea":10,"eggfriedrice":2,"chasiuriceroll":8,"porksiumai":3,"scallopsiumai":1,"saltyfishfriedrice":2,"fishcongee":10,"shrimpchips":10,"steamedrice":10,"yangchowfriedrice":9,"bakedchasiubao":10,"hotdogbun":5,"shrimpfriedrice":6,"lotusleaf":10,"spamfriedrice":9,"stuffedeggplant":10,"rabbitbun":3,"claypot":7,"chinesesausagefriedrice":4,"seafoodfriedrice":2,"shrimproll":8,"chickenfeet":7,"mangopudding":11,"mooncake":10,"guabao":4,"custardbun":10,"salmonriceroll":5,"shanghaisoupdumpling":10,"wontonnoodlesoup":8,"porkshrimpiumai":13,"shrimpriceroll":10,"chaozhoufunguo":5,"stickyricecake":7,"chasiurice":10,"pigletbun":14,"bakedlavabun":10,"greentea":5,"sausageroll":7,"puertea":5,"wintermelontea":10,"spinachandshrimpdumpling":10,"springroll":10}}}},"trainingResults":{"imageClassifier":{"confusionMatrix":[{"expected":"bakedchasiubao","actual":"bakedchasiubao","count":10},{"expected":"bakedlavabun","actual":"bakedlavabun","count":8},{"expected":"beefriceroll","actual":"beefriceroll","count":8},{"expected":"billionairefriedrice","actual":"billionairefriedrice","count":1},{"expected":"chaozhoufunguo","actual":"chaozhoufunguo","count":4},{"expected":"chasiubao","actual":"chasiubao","count":8},{"expected":"chasiufriedrice","actual":"chasiufriedrice","count":7},{"expected":"chasiupuff","actual":"chasiupuff","count":8},{"expected":"chasiurice","actual":"chasiurice","count":10},{"expected":"chasiuriceroll","actual":"chasiuriceroll","count":8},{"expected":"chickenfeet","actual":"chickenfeet","count":7},{"expected":"chinesebroccoli","actual":"chinesebroccoli","count":10},{"expected":"chinesesausagefriedrice","actual":"chinesesausagefriedrice","count":2},{"expected":"chivedumpling","actual":"chivedumpling","count":10},{"expected":"claypot","actual":"claypot","count":7},{"expected":"curryfishball","actual":"curryfishball","count":7},{"expected":"currypuff","actual":"currypuff","count":10},{"expected":"custardbun","actual":"custardbun","count":9},{"expected":"deepfrieddumpling","actual":"deepfrieddumpling","count":6},{"expected":"eggfriedrice","actual":"eggfriedrice","count":1},{"expected":"fishcongee","actual":"fishcongee","count":10},{"expected":"fishsiumai","actual":"fishsiumai","count":2},{"expected":"flakyskinbakedchasiubao","actual":"flakyskinbakedchasiubao","count":10},{"expected":"friedeggtomatonoodlesoup","actual":"friedeggtomatonoodlesoup","count":5},{"expected":"friedfishball","actual":"friedfishball","count":8},{"expected":"friedshrimp","actual":"friedshrimp","count":9},{"expected":"friedwonton","actual":"friedwonton","count":10},{"expected":"greentea","actual":"greentea","count":5},{"expected":"guabao","actual":"guabao","count":4},{"expected":"hkeggtart","actual":"hkeggtart","count":8},{"expected":"hklemonicetea","actual":"hklemonicetea","count":8},{"expected":"hotdogbun","actual":"hotdogbun","count":4},{"expected":"jasminetea","actual":"jasminetea","count":10},{"expected":"jellyfishsalad","actual":"jellyfishsalad","count":4},{"expected":"lotusleaf","actual":"lotusleaf","count":10},{"expected":"malaycake","actual":"malaycake","count":8},{"expected":"mangogreentea","actual":"mangogreentea","count":2},{"expected":"mangopudding","actual":"mangopudding","count":11},{"expected":"meatball","actual":"meatball","count":8},{"expected":"mochi","actual":"mochi","count":2},{"expected":"mooncake","actual":"mooncake","count":10},{"expected":"mushroomsiumai","actual":"mushroomsiumai","count":3},{"expected":"oolongtea","actual":"oolongtea","count":10},{"expected":"panfriedriceroll","actual":"panfriedriceroll","count":4},{"expected":"pigletbun","actual":"pigletbun","count":12},{"expected":"pineapplebun","actual":"pineapplebun","count":7},{"expected":"porkbelly","actual":"porkbelly","count":9},{"expected":"porkshrimpiumai","actual":"porkshrimpiumai","count":12},{"expected":"porksiumai","actual":"porksiumai","count":2},{"expected":"porksungbun","actual":"porksungbun","count":9},{"expected":"portugueseeggtart","actual":"portugueseeggtart","count":10},{"expected":"preservedeggporkcongee","actual":"preservedeggporkcongee","count":10},{"expected":"puertea","actual":"puertea","count":5},{"expected":"rabbitbun","actual":"rabbitbun","count":3},{"expected":"redoilwonton","actual":"redoilwonton","count":3},{"expected":"salmonriceroll","actual":"salmonriceroll","count":5},{"expected":"saltandpeppersquid","actual":"saltandpeppersquid","count":5},{"expected":"claypot","actual":"saltedfishmincedporkclaypotrice","count":1},{"expected":"saltedfishmincedporkclaypotrice","actual":"saltedfishmincedporkclaypotrice","count":5},{"expected":"saltyfishfriedrice","actual":"saltyfishfriedrice","count":2},{"expected":"sausageroll","actual":"sausageroll","count":7},{"expected":"scallopsiumai","actual":"scallopsiumai","count":1},{"expected":"seafoodfriedrice","actual":"seafoodfriedrice","count":2},{"expected":"seaweedsalad","actual":"seaweedsalad","count":5},{"expected":"sesameball","actual":"sesameball","count":9},{"expected":"shanghaisoupdumpling","actual":"shanghaisoupdumpling","count":10},{"expected":"shrimpchips","actual":"shrimpchips","count":10},{"expected":"shrimpdumpling","actual":"shrimpdumpling","count":12},{"expected":"shrimpfriedrice","actual":"shrimpfriedrice","count":6},{"expected":"shrimpriceroll","actual":"shrimpriceroll","count":9},{"expected":"shrimproll","actual":"shrimproll","count":8},{"expected":"shrimpsiumai","actual":"shrimpsiumai","count":3},{"expected":"singaporenoodles","actual":"singaporenoodles","count":10},{"expected":"spamfriedrice","actual":"spamfriedrice","count":7},{"expected":"yangchowfriedrice","actual":"spamfriedrice","count":2},{"expected":"spinachandshrimpdumpling","actual":"spinachandshrimpdumpling","count":10},{"expected":"springroll","actual":"springroll","count":8},{"expected":"steamedegg","actual":"steamedegg","count":10},{"expected":"steamedrice","actual":"steamedrice","count":10},{"expected":"stickyricecake","actual":"stickyricecake","count":6},{"expected":"stuffedeggplant","actual":"stuffedeggplant","count":9},{"expected":"stuffedtofu","actual":"stuffedtofu","count":5},{"expected":"sugarcaneshrimp","actual":"sugarcaneshrimp","count":6},{"expected":"sweetpotatosoup","actual":"sweetpotatosoup","count":8},{"expected":"tarodumpling","actual":"tarodumpling","count":10},{"expected":"tofupudding","actual":"tofupudding","count":8},{"expected":"tofuskinroll","actual":"tofuskinroll","count":10},{"expected":"turnipcake","actual":"turnipcake","count":10},{"expected":"vegetablefriedrice","actual":"vegetablefriedrice","count":2},{"expected":"vietnamesespringroll","actual":"vietnamesespringroll","count":7},{"expected":"westlakesoup","actual":"westlakesoup","count":10},{"expected":"wintermelontea","actual":"wintermelontea","count":9},{"expected":"wontonnoodlesoup","actual":"wontonnoodlesoup","count":8},{"expected":"spamfriedrice","actual":"yangchowfriedrice","count":2},{"expected":"yangchowfriedrice","actual":"yangchowfriedrice","count":7}],"statsByLabel":{"friedeggtomatonoodlesoup":{"count":5,"precisionRecall":{"success":{"recall":1,"precision":1}}},"malaycake":{"count":8,"precisionRecall":{"success":{"recall":1,"precision":1}}},"porksungbun":{"count":9,"precisionRecall":{"success":{"recall":1,"precision":1}}},"billionairefriedrice":{"count":1,"precisionRecall":{"success":{"recall":1,"precision":1}}},"panfriedriceroll":{"count":4,"precisionRecall":{"success":{"recall":1,"precision":1}}},"westlakesoup":{"count":10,"precisionRecall":{"success":{"recall":1,"precision":1}}},"chasiupuff":{"count":8,"precisionRecall":{"success":{"recall":1,"precision":1}}},"steamedegg":{"count":10,"precisionRecall":{"success":{"recall":1,"precision":1}}},"sweetpotatosoup":{"count":8,"precisionRecall":{"success":{"recall":1,"precision":1}}},"friedshrimp":{"count":9,"precisionRecall":{"success":{"recall":1,"precision":1}}},"porkbelly":{"count":9,"precisionRecall":{"success":{"recall":1,"precision":1}}},"tofuskinroll":{"count":10,"precisionRecall":{"success":{"recall":1,"precision":1}}},"chasiubao":{"count":8,"precisionRecall":{"success":{"recall":1,"precision":1}}},"deepfrieddumpling":{"count":6,"precisionRecall":{"success":{"recall":1,"precision":1}}},"mushroomsiumai":{"count":3,"precisionRecall":{"success":{"recall":1,"precision":1}}},"redoilwonton":{"count":3,"precisionRecall":{"success":{"recall":1,"precision":1}}},"jellyfishsalad":{"count":4,"precisionRecall":{"success":{"recall":1,"precision":1}}},"seaweedsalad":{"count":5,"precisionRecall":{"success":{"recall":1,"precision":1}}},"tofupudding":{"count":8,"precisionRecall":{"success":{"recall":1,"precision":1}}},"friedwonton":{"count":10,"precisionRecall":{"success":{"recall":1,"precision":1}}},"pineapplebun":{"count":7,"precisionRecall":{"success":{"recall":1,"precision":1}}},"saltandpeppersquid":{"count":5,"precisionRecall":{"success":{"recall":1,"precision":1}}},"fishsiumai":{"count":2,"precisionRecall":{"success":{"recall":1,"precision":1}}},"friedfishball":{"count":8,"precisionRecall":{"success":{"recall":1,"precision":1}}},"sugarcaneshrimp":{"count":6,"precisionRecall":{"success":{"recall":1,"precision":1}}},"shrimpsiumai":{"count":3,"precisionRecall":{"success":{"recall":1,"precision":1}}},"hklemonicetea":{"count":8,"precisionRecall":{"success":{"recall":1,"precision":1}}},"jasminetea":{"count":10,"precisionRecall":{"success":{"recall":1,"precision":1}}},"tarodumpling":{"count":10,"precisionRecall":{"success":{"recall":1,"precision":1}}},"shrimpdumpling":{"count":12,"precisionRecall":{"success":{"recall":1,"precision":1}}},"mochi":{"count":2,"precisionRecall":{"success":{"recall":1,"precision":1}}},"hkeggtart":{"count":8,"precisionRecall":{"success":{"recall":1,"precision":1}}},"flakyskinbakedchasiubao":{"count":10,"precisionRecall":{"success":{"recall":1,"precision":1}}},"currypuff":{"count":10,"precisionRecall":{"success":{"recall":1,"precision":1}}},"chinesebroccoli":{"count":10,"precisionRecall":{"success":{"recall":1,"precision":1}}},"stuffedtofu":{"count":5,"precisionRecall":{"success":{"recall":1,"precision":1}}},"preservedeggporkcongee":{"count":10,"precisionRecall":{"success":{"recall":1,"precision":1}}},"vegetablefriedrice":{"count":2,"precisionRecall":{"success":{"recall":1,"precision":1}}},"chivedumpling":{"count":10,"precisionRecall":{"success":{"recall":1,"precision":1}}},"curryfishball":{"count":7,"precisionRecall":{"success":{"recall":1,"precision":1}}},"turnipcake":{"count":10,"precisionRecall":{"success":{"recall":1,"precision":1}}},"meatball":{"count":8,"precisionRecall":{"success":{"recall":1,"precision":1}}},"vietnamesespringroll":{"count":7,"precisionRecall":{"success":{"recall":1,"precision":1}}},"singaporenoodles":{"count":10,"precisionRecall":{"success":{"recall":1,"precision":1}}},"portugueseeggtart":{"count":10,"precisionRecall":{"success":{"recall":1,"precision":1}}},"saltedfishmincedporkclaypotrice":{"count":6,"precisionRecall":{"success":{"recall":0.83333333333333337,"precision":1}}},"beefriceroll":{"count":8,"precisionRecall":{"success":{"recall":1,"precision":1}}},"mangogreentea":{"count":2,"precisionRecall":{"success":{"recall":1,"precision":1}}},"sesameball":{"count":9,"precisionRecall":{"success":{"recall":1,"precision":1}}},"chasiufriedrice":{"count":7,"precisionRecall":{"success":{"recall":1,"precision":1}}},"oolongtea":{"count":10,"precisionRecall":{"success":{"recall":1,"precision":1}}},"eggfriedrice":{"count":1,"precisionRecall":{"success":{"recall":1,"precision":1}}},"chasiuriceroll":{"count":8,"precisionRecall":{"success":{"recall":1,"precision":1}}},"porksiumai":{"count":2,"precisionRecall":{"success":{"recall":1,"precision":1}}},"scallopsiumai":{"count":1,"precisionRecall":{"success":{"recall":1,"precision":1}}},"saltyfishfriedrice":{"count":2,"precisionRecall":{"success":{"recall":1,"precision":1}}},"fishcongee":{"count":10,"precisionRecall":{"success":{"recall":1,"precision":1}}},"shrimpchips":{"count":10,"precisionRecall":{"success":{"recall":1,"precision":1}}},"steamedrice":{"count":10,"precisionRecall":{"success":{"recall":1,"precision":1}}},"yangchowfriedrice":{"count":9,"precisionRecall":{"success":{"recall":0.77777777777777779,"precision":0.77777777777777779}}},"bakedchasiubao":{"count":10,"precisionRecall":{"success":{"recall":1,"precision":1}}},"hotdogbun":{"count":4,"precisionRecall":{"success":{"recall":1,"precision":1}}},"shrimpfriedrice":{"count":6,"precisionRecall":{"success":{"recall":1,"precision":1}}},"lotusleaf":{"count":10,"precisionRecall":{"success":{"recall":1,"precision":1}}},"spamfriedrice":{"count":9,"precisionRecall":{"success":{"recall":0.77777777777777779,"precision":0.77777777777777779}}},"stuffedeggplant":{"count":9,"precisionRecall":{"success":{"recall":1,"precision":1}}},"rabbitbun":{"count":3,"precisionRecall":{"success":{"recall":1,"precision":1}}},"claypot":{"count":7,"precisionRecall":{"success":{"recall":1,"precision":0.875}}},"chinesesausagefriedrice":{"count":2,"precisionRecall":{"success":{"recall":1,"precision":1}}},"seafoodfriedrice":{"count":2,"precisionRecall":{"success":{"recall":1,"precision":1}}},"shrimproll":{"count":8,"precisionRecall":{"success":{"recall":1,"precision":1}}},"chickenfeet":{"count":7,"precisionRecall":{"success":{"recall":1,"precision":1}}},"mangopudding":{"count":11,"precisionRecall":{"success":{"recall":1,"precision":1}}},"mooncake":{"count":10,"precisionRecall":{"success":{"recall":1,"precision":1}}},"guabao":{"count":4,"precisionRecall":{"success":{"recall":1,"precision":1}}},"custardbun":{"count":9,"precisionRecall":{"success":{"recall":1,"precision":1}}},"salmonriceroll":{"count":5,"precisionRecall":{"success":{"recall":1,"precision":1}}},"shanghaisoupdumpling":{"count":10,"precisionRecall":{"success":{"recall":1,"precision":1}}},"wontonnoodlesoup":{"count":8,"precisionRecall":{"success":{"recall":1,"precision":1}}},"porkshrimpiumai":{"count":12,"precisionRecall":{"success":{"recall":1,"precision":1}}},"shrimpriceroll":{"count":9,"precisionRecall":{"success":{"recall":1,"precision":1}}},"chaozhoufunguo":{"count":4,"precisionRecall":{"success":{"recall":1,"precision":1}}},"stickyricecake":{"count":6,"precisionRecall":{"success":{"recall":1,"precision":1}}},"chasiurice":{"count":10,"precisionRecall":{"success":{"recall":1,"precision":1}}},"pigletbun":{"count":12,"precisionRecall":{"success":{"recall":1,"precision":1}}},"bakedlavabun":{"count":8,"precisionRecall":{"success":{"recall":1,"precision":1}}},"greentea":{"count":5,"precisionRecall":{"success":{"recall":1,"precision":1}}},"sausageroll":{"count":7,"precisionRecall":{"success":{"recall":1,"precision":1}}},"puertea":{"count":5,"precisionRecall":{"success":{"recall":1,"precision":1}}},"wintermelontea":{"count":9,"precisionRecall":{"success":{"recall":1,"precision":1}}},"spinachandshrimpdumpling":{"count":10,"precisionRecall":{"success":{"recall":1,"precision":1}}},"springroll":{"count":8,"precisionRecall":{"success":{"recall":1,"precision":1}}}},"accuracy":0.99244712990936557}},"progress":[{"currentRowIndex":0,"tableIndex":0,"count":0,"isLast":false,"percentComplete":0,"tableDone":false},{"icTrainingColumnHeader":{"hasValidation":true,"elapsedTime":0.48033900000000002,"trainingAccuracy":0.25075500000000001,"iterationCount":1,"validationAccuracy":0.074999999999999997},"isLast":false,"currentRowIndex":0,"count":1,"tableDone":false,"tableIndex":141,"percentComplete":0},{"icTrainingColumnHeader":{"hasValidation":true,"elapsedTime":1.1830160000000001,"trainingAccuracy":0.58006000000000002,"iterationCount":2,"validationAccuracy":0.22500000000000001},"isLast":false,"currentRowIndex":0,"count":2,"tableDone":false,"tableIndex":141,"percentComplete":0},{"icTrainingColumnHeader":{"hasValidation":true,"elapsedTime":1.8447089999999999,"trainingAccuracy":0.75830799999999998,"iterationCount":3,"validationAccuracy":0.47499999999999998},"isLast":false,"currentRowIndex":0,"count":3,"tableDone":false,"tableIndex":141,"percentComplete":0},{"icTrainingColumnHeader":{"hasValidation":true,"elapsedTime":2.329882,"trainingAccuracy":0.79154100000000005,"iterationCount":4,"validationAccuracy":0.42499999999999999},"isLast":false,"currentRowIndex":0,"count":4,"tableDone":false,"tableIndex":141,"percentComplete":0},{"icTrainingColumnHeader":{"hasValidation":true,"elapsedTime":2.864436,"trainingAccuracy":0.85347399999999995,"iterationCount":5,"validationAccuracy":0.5},"isLast":false,"currentRowIndex":0,"count":5,"tableDone":false,"tableIndex":141,"percentComplete":0},{"icTrainingColumnHeader":{"hasValidation":true,"elapsedTime":5.1344349999999999,"trainingAccuracy":0.939577,"iterationCount":10,"validationAccuracy":0.55000000000000004},"isLast":false,"currentRowIndex":0,"count":10,"tableDone":false,"tableIndex":141,"percentComplete":0},{"currentRowIndex":0,"tableIndex":0,"count":15,"isLast":false,"percentComplete":0,"tableDone":false},{"icTrainingColumnHeader":{"hasValidation":true,"elapsedTime":10.919536000000001,"trainingAccuracy":0.98036299999999998,"iterationCount":20,"validationAccuracy":0.69999999999999996},"isLast":false,"currentRowIndex":0,"count":20,"tableDone":false,"tableIndex":141,"percentComplete":0},{"icTrainingColumnHeader":{"hasValidation":true,"elapsedTime":14.665893000000001,"trainingAccuracy":0.99244699999999997,"iterationCount":25,"validationAccuracy":0.67500000000000004},"isLast":false,"currentRowIndex":0,"count":25,"tableDone":true,"tableIndex":141,"percentComplete":0},{"currentRowIndex":0,"tableIndex":0,"count":30,"isLast":false,"percentComplete":0,"tableDone":false},{"currentRowIndex":0,"tableIndex":0,"count":35,"isLast":false,"percentComplete":0,"tableDone":false},{"currentRowIndex":0,"tableIndex":0,"count":40,"isLast":false,"percentComplete":0,"tableDone":false},{"currentRowIndex":0,"tableIndex":0,"count":45,"isLast":false,"percentComplete":0,"tableDone":false},{"currentRowIndex":0,"tableIndex":0,"count":50,"isLast":false,"percentComplete":0,"tableDone":false},{"currentRowIndex":0,"tableIndex":0,"count":55,"isLast":false,"percentComplete":0,"tableDone":false},{"currentRowIndex":0,"tableIndex":0,"count":60,"isLast":false,"percentComplete":0,"tableDone":false},{"currentRowIndex":0,"tableIndex":0,"count":65,"isLast":false,"percentComplete":0,"tableDone":false},{"currentRowIndex":0,"tableIndex":0,"count":70,"isLast":false,"percentComplete":0,"tableDone":false},{"currentRowIndex":0,"tableIndex":0,"count":75,"isLast":false,"percentComplete":0,"tableDone":false},{"currentRowIndex":0,"tableIndex":0,"count":80,"isLast":false,"percentComplete":0,"tableDone":false},{"currentRowIndex":0,"tableIndex":0,"count":85,"isLast":false,"percentComplete":0,"tableDone":false},{"currentRowIndex":0,"tableIndex":0,"count":90,"isLast":false,"percentComplete":0,"tableDone":false},{"currentRowIndex":0,"tableIndex":0,"count":95,"isLast":false,"percentComplete":0,"tableDone":false},{"currentRowIndex":0,"tableIndex":0,"count":100,"isLast":false,"percentComplete":0,"tableDone":false},{"currentRowIndex":0,"tableIndex":0,"count":105,"isLast":false,"percentComplete":0,"tableDone":false},{"currentRowIndex":0,"tableIndex":0,"count":110,"isLast":false,"percentComplete":0,"tableDone":false},{"currentRowIndex":0,"tableIndex":0,"count":115,"isLast":false,"percentComplete":0,"tableDone":false},{"currentRowIndex":0,"tableIndex":0,"count":120,"isLast":false,"percentComplete":0,"tableDone":false},{"currentRowIndex":0,"tableIndex":0,"count":125,"isLast":false,"percentComplete":0,"tableDone":false},{"currentRowIndex":0,"tableIndex":0,"count":130,"isLast":false,"percentComplete":0,"tableDone":false},{"currentRowIndex":0,"tableIndex":0,"count":135,"isLast":false,"percentComplete":0,"tableDone":false},{"currentRowIndex":0,"tableIndex":0,"count":140,"isLast":false,"percentComplete":0,"tableDone":false},{"currentRowIndex":0,"tableIndex":0,"count":145,"isLast":false,"percentComplete":0,"tableDone":false},{"currentRowIndex":0,"tableIndex":0,"count":150,"isLast":false,"percentComplete":0,"tableDone":false},{"currentRowIndex":0,"tableIndex":0,"count":155,"isLast":false,"percentComplete":0,"tableDone":false},{"currentRowIndex":0,"tableIndex":0,"count":160,"isLast":false,"percentComplete":0,"tableDone":false},{"currentRowIndex":0,"tableIndex":0,"count":165,"isLast":false,"percentComplete":0,"tableDone":false},{"currentRowIndex":0,"tableIndex":0,"count":170,"isLast":false,"percentComplete":0,"tableDone":false},{"currentRowIndex":0,"tableIndex":0,"count":175,"isLast":false,"percentComplete":0,"tableDone":false},{"currentRowIndex":0,"tableIndex":0,"count":180,"isLast":false,"percentComplete":0,"tableDone":false},{"currentRowIndex":0,"tableIndex":0,"count":185,"isLast":false,"percentComplete":0,"tableDone":false},{"currentRowIndex":0,"tableIndex":0,"count":190,"isLast":false,"percentComplete":0,"tableDone":false},{"currentRowIndex":0,"tableIndex":0,"count":195,"isLast":false,"percentComplete":0,"tableDone":false},{"currentRowIndex":0,"tableIndex":0,"count":200,"isLast":false,"percentComplete":0,"tableDone":false},{"currentRowIndex":0,"tableIndex":0,"count":205,"isLast":false,"percentComplete":0,"tableDone":false},{"currentRowIndex":0,"tableIndex":0,"count":210,"isLast":false,"percentComplete":0,"tableDone":false},{"currentRowIndex":0,"tableIndex":0,"count":215,"isLast":false,"percentComplete":0,"tableDone":false},{"currentRowIndex":0,"tableIndex":0,"count":220,"isLast":false,"percentComplete":0,"tableDone":false},{"currentRowIndex":0,"tableIndex":0,"count":225,"isLast":false,"percentComplete":0,"tableDone":false},{"currentRowIndex":0,"tableIndex":0,"count":230,"isLast":false,"percentComplete":0,"tableDone":false},{"currentRowIndex":0,"tableIndex":0,"count":235,"isLast":false,"percentComplete":0,"tableDone":false},{"currentRowIndex":0,"tableIndex":0,"count":240,"isLast":false,"percentComplete":0,"tableDone":false},{"currentRowIndex":0,"tableIndex":0,"count":245,"isLast":false,"percentComplete":0,"tableDone":false},{"currentRowIndex":0,"tableIndex":0,"count":250,"isLast":false,"percentComplete":0,"tableDone":false},{"currentRowIndex":0,"tableIndex":0,"count":255,"isLast":false,"percentComplete":0,"tableDone":false},{"currentRowIndex":0,"tableIndex":0,"count":260,"isLast":false,"percentComplete":0,"tableDone":false},{"currentRowIndex":0,"tableIndex":0,"count":265,"isLast":false,"percentComplete":0,"tableDone":false},{"currentRowIndex":0,"tableIndex":0,"count":270,"isLast":false,"percentComplete":0,"tableDone":false},{"currentRowIndex":0,"tableIndex":0,"count":275,"isLast":false,"percentComplete":0,"tableDone":false},{"currentRowIndex":0,"tableIndex":0,"count":280,"isLast":false,"percentComplete":0,"tableDone":false},{"currentRowIndex":0,"tableIndex":0,"count":285,"isLast":false,"percentComplete":0,"tableDone":false},{"currentRowIndex":0,"tableIndex":0,"count":290,"isLast":false,"percentComplete":0,"tableDone":false},{"currentRowIndex":0,"tableIndex":0,"count":295,"isLast":false,"percentComplete":0,"tableDone":false},{"currentRowIndex":0,"tableIndex":0,"count":300,"isLast":false,"percentComplete":0,"tableDone":false},{"currentRowIndex":0,"tableIndex":0,"count":305,"isLast":false,"percentComplete":0,"tableDone":false},{"currentRowIndex":0,"tableIndex":0,"count":310,"isLast":false,"percentComplete":0,"tableDone":false},{"currentRowIndex":0,"tableIndex":0,"count":315,"isLast":false,"percentComplete":0,"tableDone":false},{"currentRowIndex":0,"tableIndex":0,"count":320,"isLast":false,"percentComplete":0,"tableDone":false},{"currentRowIndex":0,"tableIndex":0,"count":325,"isLast":false,"percentComplete":0,"tableDone":false},{"currentRowIndex":0,"tableIndex":0,"count":330,"isLast":false,"percentComplete":0,"tableDone":false},{"currentRowIndex":0,"tableIndex":0,"count":335,"isLast":false,"percentComplete":0,"tableDone":false},{"currentRowIndex":0,"tableIndex":0,"count":340,"isLast":false,"percentComplete":0,"tableDone":false},{"currentRowIndex":0,"tableIndex":0,"count":345,"isLast":false,"percentComplete":0,"tableDone":false},{"currentRowIndex":0,"tableIndex":0,"count":350,"isLast":false,"percentComplete":0,"tableDone":false},{"currentRowIndex":0,"tableIndex":0,"count":355,"isLast":false,"percentComplete":0,"tableDone":false},{"currentRowIndex":0,"tableIndex":0,"count":360,"isLast":false,"percentComplete":0,"tableDone":false},{"currentRowIndex":0,"tableIndex":0,"count":365,"isLast":false,"percentComplete":0,"tableDone":false},{"currentRowIndex":0,"tableIndex":0,"count":370,"isLast":false,"percentComplete":0,"tableDone":false},{"currentRowIndex":0,"tableIndex":0,"count":375,"isLast":false,"percentComplete":0,"tableDone":false},{"currentRowIndex":0,"tableIndex":0,"count":380,"isLast":false,"percentComplete":0,"tableDone":false},{"currentRowIndex":0,"tableIndex":0,"count":385,"isLast":false,"percentComplete":0,"tableDone":false},{"currentRowIndex":0,"tableIndex":0,"count":390,"isLast":false,"percentComplete":0,"tableDone":false},{"currentRowIndex":0,"tableIndex":0,"count":395,"isLast":false,"percentComplete":0,"tableDone":false},{"currentRowIndex":0,"tableIndex":0,"count":400,"isLast":false,"percentComplete":0,"tableDone":false},{"currentRowIndex":0,"tableIndex":0,"count":405,"isLast":false,"percentComplete":0,"tableDone":false},{"currentRowIndex":0,"tableIndex":0,"count":410,"isLast":false,"percentComplete":0,"tableDone":false},{"currentRowIndex":0,"tableIndex":0,"count":415,"isLast":false,"percentComplete":0,"tableDone":false},{"currentRowIndex":0,"tableIndex":0,"count":420,"isLast":false,"percentComplete":0,"tableDone":false},{"currentRowIndex":0,"tableIndex":0,"count":425,"isLast":false,"percentComplete":0,"tableDone":false},{"currentRowIndex":0,"tableIndex":0,"count":430,"isLast":false,"percentComplete":0,"tableDone":false},{"currentRowIndex":0,"tableIndex":0,"count":435,"isLast":false,"percentComplete":0,"tableDone":false},{"currentRowIndex":0,"tableIndex":0,"count":440,"isLast":false,"percentComplete":0,"tableDone":false},{"currentRowIndex":0,"tableIndex":0,"count":445,"isLast":false,"percentComplete":0,"tableDone":false},{"currentRowIndex":0,"tableIndex":0,"count":450,"isLast":false,"percentComplete":0,"tableDone":false},{"currentRowIndex":0,"tableIndex":0,"count":455,"isLast":false,"percentComplete":0,"tableDone":false},{"currentRowIndex":0,"tableIndex":0,"count":460,"isLast":false,"percentComplete":0,"tableDone":false},{"currentRowIndex":0,"tableIndex":0,"count":465,"isLast":false,"percentComplete":0,"tableDone":false},{"currentRowIndex":0,"tableIndex":0,"count":470,"isLast":false,"percentComplete":0,"tableDone":false},{"currentRowIndex":0,"tableIndex":0,"count":475,"isLast":false,"percentComplete":0,"tableDone":false},{"currentRowIndex":0,"tableIndex":0,"count":480,"isLast":false,"percentComplete":0,"tableDone":false},{"currentRowIndex":0,"tableIndex":0,"count":485,"isLast":false,"percentComplete":0,"tableDone":false},{"currentRowIndex":0,"tableIndex":0,"count":490,"isLast":false,"percentComplete":0,"tableDone":false},{"currentRowIndex":0,"tableIndex":0,"count":495,"isLast":false,"percentComplete":0,"tableDone":false},{"currentRowIndex":0,"tableIndex":0,"count":500,"isLast":false,"percentComplete":0,"tableDone":false},{"currentRowIndex":0,"tableIndex":0,"count":505,"isLast":false,"percentComplete":0,"tableDone":false},{"currentRowIndex":0,"tableIndex":0,"count":510,"isLast":false,"percentComplete":0,"tableDone":false},{"currentRowIndex":0,"tableIndex":0,"count":515,"isLast":false,"percentComplete":0,"tableDone":false},{"currentRowIndex":0,"tableIndex":0,"count":520,"isLast":false,"percentComplete":0,"tableDone":false},{"currentRowIndex":0,"tableIndex":0,"count":525,"isLast":false,"percentComplete":0,"tableDone":false},{"currentRowIndex":0,"tableIndex":0,"count":530,"isLast":false,"percentComplete":0,"tableDone":false},{"currentRowIndex":0,"tableIndex":0,"count":535,"isLast":false,"percentComplete":0,"tableDone":false},{"currentRowIndex":0,"tableIndex":0,"count":540,"isLast":false,"percentComplete":0,"tableDone":false},{"currentRowIndex":0,"tableIndex":0,"count":545,"isLast":false,"percentComplete":0,"tableDone":false},{"currentRowIndex":0,"tableIndex":0,"count":550,"isLast":false,"percentComplete":0,"tableDone":false},{"currentRowIndex":0,"tableIndex":0,"count":555,"isLast":false,"percentComplete":0,"tableDone":false},{"currentRowIndex":0,"tableIndex":0,"count":560,"isLast":false,"percentComplete":0,"tableDone":false},{"currentRowIndex":0,"tableIndex":0,"count":565,"isLast":false,"percentComplete":0,"tableDone":false},{"currentRowIndex":0,"tableIndex":0,"count":570,"isLast":false,"percentComplete":0,"tableDone":false},{"currentRowIndex":0,"tableIndex":0,"count":575,"isLast":false,"percentComplete":0,"tableDone":false},{"currentRowIndex":0,"tableIndex":0,"count":580,"isLast":false,"percentComplete":0,"tableDone":false},{"currentRowIndex":0,"tableIndex":0,"count":585,"isLast":false,"percentComplete":0,"tableDone":false},{"currentRowIndex":0,"tableIndex":0,"count":590,"isLast":false,"percentComplete":0,"tableDone":false},{"currentRowIndex":0,"tableIndex":0,"count":595,"isLast":false,"percentComplete":0,"tableDone":false},{"currentRowIndex":0,"tableIndex":0,"count":600,"isLast":false,"percentComplete":0,"tableDone":false},{"currentRowIndex":0,"tableIndex":0,"count":605,"isLast":false,"percentComplete":0,"tableDone":false},{"currentRowIndex":0,"tableIndex":0,"count":610,"isLast":false,"percentComplete":0,"tableDone":false},{"currentRowIndex":0,"tableIndex":0,"count":615,"isLast":false,"percentComplete":0,"tableDone":false},{"currentRowIndex":0,"tableIndex":0,"count":620,"isLast":false,"percentComplete":0,"tableDone":false},{"currentRowIndex":0,"tableIndex":0,"count":625,"isLast":false,"percentComplete":0,"tableDone":false},{"currentRowIndex":0,"tableIndex":0,"count":630,"isLast":false,"percentComplete":0,"tableDone":false},{"currentRowIndex":0,"tableIndex":0,"count":635,"isLast":false,"percentComplete":0,"tableDone":false},{"currentRowIndex":0,"tableIndex":0,"count":640,"isLast":false,"percentComplete":0,"tableDone":false},{"currentRowIndex":0,"tableIndex":0,"count":645,"isLast":false,"percentComplete":0,"tableDone":false},{"currentRowIndex":0,"tableIndex":0,"count":650,"isLast":false,"percentComplete":0,"tableDone":false},{"currentRowIndex":0,"tableIndex":0,"count":655,"isLast":false,"percentComplete":0,"tableDone":false},{"currentRowIndex":0,"tableIndex":0,"count":660,"isLast":false,"percentComplete":0,"tableDone":false},{"currentRowIndex":0,"tableIndex":0,"count":665,"isLast":false,"percentComplete":0,"tableDone":false},{"currentRowIndex":0,"tableIndex":0,"count":670,"isLast":false,"percentComplete":0,"tableDone":false},{"currentRowIndex":0,"tableIndex":0,"count":675,"isLast":false,"percentComplete":0,"tableDone":false},{"currentRowIndex":0,"tableIndex":0,"count":680,"isLast":false,"percentComplete":0,"tableDone":false},{"currentRowIndex":0,"tableIndex":0,"count":685,"isLast":false,"percentComplete":0,"tableDone":false},{"currentRowIndex":0,"tableIndex":0,"count":690,"isLast":false,"percentComplete":0,"tableDone":false},{"currentRowIndex":0,"tableIndex":0,"count":695,"isLast":false,"percentComplete":0,"tableDone":false},{"currentRowIndex":0,"tableIndex":0,"count":700,"isLast":false,"percentComplete":0,"tableDone":false},{"currentRowIndex":0,"tableIndex":0,"count":702,"isLast":false,"percentComplete":0,"tableDone":true}],"trainingAccuracy":0.99244712990936557,"checkpointMetrics":{},"analysedDataType":"datasource","dataSourceID":"384A0C1F-BB47-4B79-9D3C-A28B7D418D05","snapshottableCheckpoints":{},"featureExtractionCheckpointMayBeAvailable":false,"validationAccuracy":0.67500000000000004,"startTime":"2022-10-30T23:57:59Z"},"createdDate":"2022-10-30T23:57:49Z","evaluationContainerEntity":{"testingEvaluationEntity":{"id":"a7490aaf-deb4-4cb3-886c-ee3208184dbe","createdDate":"2022-10-30T23:57:49Z","dataResult":{"createdDate":"2022-10-30T23:57:49Z"},"analysedDataType":"none"},"createdDate":"2022-10-30T23:59:27Z","id":"e238c45c-1109-4088-b7b7-74ad447c3674","trainingEvaluationEntity":{"evaluationResult":{"imageClassifier":{"confusionMatrix":[{"expected":"bakedchasiubao","actual":"bakedchasiubao","count":10},{"expected":"bakedlavabun","actual":"bakedlavabun","count":8},{"expected":"beefriceroll","actual":"beefriceroll","count":8},{"expected":"billionairefriedrice","actual":"billionairefriedrice","count":1},{"expected":"chaozhoufunguo","actual":"chaozhoufunguo","count":4},{"expected":"chasiubao","actual":"chasiubao","count":8},{"expected":"chasiufriedrice","actual":"chasiufriedrice","count":7},{"expected":"chasiupuff","actual":"chasiupuff","count":8},{"expected":"chasiurice","actual":"chasiurice","count":10},{"expected":"chasiuriceroll","actual":"chasiuriceroll","count":8},{"expected":"chickenfeet","actual":"chickenfeet","count":7},{"expected":"chinesebroccoli","actual":"chinesebroccoli","count":10},{"expected":"chinesesausagefriedrice","actual":"chinesesausagefriedrice","count":2},{"expected":"chivedumpling","actual":"chivedumpling","count":10},{"expected":"claypot","actual":"claypot","count":7},{"expected":"curryfishball","actual":"curryfishball","count":7},{"expected":"currypuff","actual":"currypuff","count":10},{"expected":"custardbun","actual":"custardbun","count":9},{"expected":"deepfrieddumpling","actual":"deepfrieddumpling","count":6},{"expected":"eggfriedrice","actual":"eggfriedrice","count":1},{"expected":"fishcongee","actual":"fishcongee","count":10},{"expected":"fishsiumai","actual":"fishsiumai","count":2},{"expected":"flakyskinbakedchasiubao","actual":"flakyskinbakedchasiubao","count":10},{"expected":"friedeggtomatonoodlesoup","actual":"friedeggtomatonoodlesoup","count":5},{"expected":"friedfishball","actual":"friedfishball","count":8},{"expected":"friedshrimp","actual":"friedshrimp","count":9},{"expected":"friedwonton","actual":"friedwonton","count":10},{"expected":"greentea","actual":"greentea","count":5},{"expected":"guabao","actual":"guabao","count":4},{"expected":"hkeggtart","actual":"hkeggtart","count":8},{"expected":"hklemonicetea","actual":"hklemonicetea","count":8},{"expected":"hotdogbun","actual":"hotdogbun","count":4},{"expected":"jasminetea","actual":"jasminetea","count":10},{"expected":"jellyfishsalad","actual":"jellyfishsalad","count":4},{"expected":"lotusleaf","actual":"lotusleaf","count":10},{"expected":"malaycake","actual":"malaycake","count":8},{"expected":"mangogreentea","actual":"mangogreentea","count":2},{"expected":"mangopudding","actual":"mangopudding","count":11},{"expected":"meatball","actual":"meatball","count":8},{"expected":"mochi","actual":"mochi","count":2},{"expected":"mooncake","actual":"mooncake","count":10},{"expected":"mushroomsiumai","actual":"mushroomsiumai","count":3},{"expected":"oolongtea","actual":"oolongtea","count":10},{"expected":"panfriedriceroll","actual":"panfriedriceroll","count":4},{"expected":"pigletbun","actual":"pigletbun","count":12},{"expected":"pineapplebun","actual":"pineapplebun","count":7},{"expected":"porkbelly","actual":"porkbelly","count":9},{"expected":"porkshrimpiumai","actual":"porkshrimpiumai","count":12},{"expected":"porksiumai","actual":"porksiumai","count":2},{"expected":"porksungbun","actual":"porksungbun","count":9},{"expected":"portugueseeggtart","actual":"portugueseeggtart","count":10},{"expected":"preservedeggporkcongee","actual":"preservedeggporkcongee","count":10},{"expected":"puertea","actual":"puertea","count":5},{"expected":"rabbitbun","actual":"rabbitbun","count":3},{"expected":"redoilwonton","actual":"redoilwonton","count":3},{"expected":"salmonriceroll","actual":"salmonriceroll","count":5},{"expected":"saltandpeppersquid","actual":"saltandpeppersquid","count":5},{"expected":"claypot","actual":"saltedfishmincedporkclaypotrice","count":1},{"expected":"saltedfishmincedporkclaypotrice","actual":"saltedfishmincedporkclaypotrice","count":5},{"expected":"saltyfishfriedrice","actual":"saltyfishfriedrice","count":2},{"expected":"sausageroll","actual":"sausageroll","count":7},{"expected":"scallopsiumai","actual":"scallopsiumai","count":1},{"expected":"seafoodfriedrice","actual":"seafoodfriedrice","count":2},{"expected":"seaweedsalad","actual":"seaweedsalad","count":5},{"expected":"sesameball","actual":"sesameball","count":9},{"expected":"shanghaisoupdumpling","actual":"shanghaisoupdumpling","count":10},{"expected":"shrimpchips","actual":"shrimpchips","count":10},{"expected":"shrimpdumpling","actual":"shrimpdumpling","count":12},{"expected":"shrimpfriedrice","actual":"shrimpfriedrice","count":6},{"expected":"shrimpriceroll","actual":"shrimpriceroll","count":9},{"expected":"shrimproll","actual":"shrimproll","count":8},{"expected":"shrimpsiumai","actual":"shrimpsiumai","count":3},{"expected":"singaporenoodles","actual":"singaporenoodles","count":10},{"expected":"spamfriedrice","actual":"spamfriedrice","count":7},{"expected":"yangchowfriedrice","actual":"spamfriedrice","count":2},{"expected":"spinachandshrimpdumpling","actual":"spinachandshrimpdumpling","count":10},{"expected":"springroll","actual":"springroll","count":8},{"expected":"steamedegg","actual":"steamedegg","count":10},{"expected":"steamedrice","actual":"steamedrice","count":10},{"expected":"stickyricecake","actual":"stickyricecake","count":6},{"expected":"stuffedeggplant","actual":"stuffedeggplant","count":9},{"expected":"stuffedtofu","actual":"stuffedtofu","count":5},{"expected":"sugarcaneshrimp","actual":"sugarcaneshrimp","count":6},{"expected":"sweetpotatosoup","actual":"sweetpotatosoup","count":8},{"expected":"tarodumpling","actual":"tarodumpling","count":10},{"expected":"tofupudding","actual":"tofupudding","count":8},{"expected":"tofuskinroll","actual":"tofuskinroll","count":10},{"expected":"turnipcake","actual":"turnipcake","count":10},{"expected":"vegetablefriedrice","actual":"vegetablefriedrice","count":2},{"expected":"vietnamesespringroll","actual":"vietnamesespringroll","count":7},{"expected":"westlakesoup","actual":"westlakesoup","count":10},{"expected":"wintermelontea","actual":"wintermelontea","count":9},{"expected":"wontonnoodlesoup","actual":"wontonnoodlesoup","count":8},{"expected":"spamfriedrice","actual":"yangchowfriedrice","count":2},{"expected":"yangchowfriedrice","actual":"yangchowfriedrice","count":7}],"statsByLabel":{"friedeggtomatonoodlesoup":{"count":5,"precisionRecall":{"success":{"recall":1,"precision":1}}},"malaycake":{"count":8,"precisionRecall":{"success":{"recall":1,"precision":1}}},"porksungbun":{"count":9,"precisionRecall":{"success":{"recall":1,"precision":1}}},"billionairefriedrice":{"count":1,"precisionRecall":{"success":{"recall":1,"precision":1}}},"panfriedriceroll":{"count":4,"precisionRecall":{"success":{"recall":1,"precision":1}}},"westlakesoup":{"count":10,"precisionRecall":{"success":{"recall":1,"precision":1}}},"chasiupuff":{"count":8,"precisionRecall":{"success":{"recall":1,"precision":1}}},"steamedegg":{"count":10,"precisionRecall":{"success":{"recall":1,"precision":1}}},"sweetpotatosoup":{"count":8,"precisionRecall":{"success":{"recall":1,"precision":1}}},"friedshrimp":{"count":9,"precisionRecall":{"success":{"recall":1,"precision":1}}},"porkbelly":{"count":9,"precisionRecall":{"success":{"recall":1,"precision":1}}},"tofuskinroll":{"count":10,"precisionRecall":{"success":{"recall":1,"precision":1}}},"chasiubao":{"count":8,"precisionRecall":{"success":{"recall":1,"precision":1}}},"deepfrieddumpling":{"count":6,"precisionRecall":{"success":{"recall":1,"precision":1}}},"mushroomsiumai":{"count":3,"precisionRecall":{"success":{"recall":1,"precision":1}}},"redoilwonton":{"count":3,"precisionRecall":{"success":{"recall":1,"precision":1}}},"jellyfishsalad":{"count":4,"precisionRecall":{"success":{"recall":1,"precision":1}}},"seaweedsalad":{"count":5,"precisionRecall":{"success":{"recall":1,"precision":1}}},"tofupudding":{"count":8,"precisionRecall":{"success":{"recall":1,"precision":1}}},"friedwonton":{"count":10,"precisionRecall":{"success":{"recall":1,"precision":1}}},"fishsiumai":{"count":2,"precisionRecall":{"success":{"recall":1,"precision":1}}},"pineapplebun":{"count":7,"precisionRecall":{"success":{"recall":1,"precision":1}}},"saltandpeppersquid":{"count":5,"precisionRecall":{"success":{"recall":1,"precision":1}}},"friedfishball":{"count":8,"precisionRecall":{"success":{"recall":1,"precision":1}}},"sugarcaneshrimp":{"count":6,"precisionRecall":{"success":{"recall":1,"precision":1}}},"shrimpsiumai":{"count":3,"precisionRecall":{"success":{"recall":1,"precision":1}}},"hklemonicetea":{"count":8,"precisionRecall":{"success":{"recall":1,"precision":1}}},"jasminetea":{"count":10,"precisionRecall":{"success":{"recall":1,"precision":1}}},"tarodumpling":{"count":10,"precisionRecall":{"success":{"recall":1,"precision":1}}},"shrimpdumpling":{"count":12,"precisionRecall":{"success":{"recall":1,"precision":1}}},"mochi":{"count":2,"precisionRecall":{"success":{"recall":1,"precision":1}}},"hkeggtart":{"count":8,"precisionRecall":{"success":{"recall":1,"precision":1}}},"flakyskinbakedchasiubao":{"count":10,"precisionRecall":{"success":{"recall":1,"precision":1}}},"currypuff":{"count":10,"precisionRecall":{"success":{"recall":1,"precision":1}}},"chinesebroccoli":{"count":10,"precisionRecall":{"success":{"recall":1,"precision":1}}},"stuffedtofu":{"count":5,"precisionRecall":{"success":{"recall":1,"precision":1}}},"preservedeggporkcongee":{"count":10,"precisionRecall":{"success":{"recall":1,"precision":1}}},"vegetablefriedrice":{"count":2,"precisionRecall":{"success":{"recall":1,"precision":1}}},"chivedumpling":{"count":10,"precisionRecall":{"success":{"recall":1,"precision":1}}},"curryfishball":{"count":7,"precisionRecall":{"success":{"recall":1,"precision":1}}},"turnipcake":{"count":10,"precisionRecall":{"success":{"recall":1,"precision":1}}},"meatball":{"count":8,"precisionRecall":{"success":{"recall":1,"precision":1}}},"vietnamesespringroll":{"count":7,"precisionRecall":{"success":{"recall":1,"precision":1}}},"singaporenoodles":{"count":10,"precisionRecall":{"success":{"recall":1,"precision":1}}},"portugueseeggtart":{"count":10,"precisionRecall":{"success":{"recall":1,"precision":1}}},"saltedfishmincedporkclaypotrice":{"count":6,"precisionRecall":{"success":{"recall":0.83333333333333337,"precision":1}}},"beefriceroll":{"count":8,"precisionRecall":{"success":{"recall":1,"precision":1}}},"mangogreentea":{"count":2,"precisionRecall":{"success":{"recall":1,"precision":1}}},"sesameball":{"count":9,"precisionRecall":{"success":{"recall":1,"precision":1}}},"chasiufriedrice":{"count":7,"precisionRecall":{"success":{"recall":1,"precision":1}}},"oolongtea":{"count":10,"precisionRecall":{"success":{"recall":1,"precision":1}}},"eggfriedrice":{"count":1,"precisionRecall":{"success":{"recall":1,"precision":1}}},"chasiuriceroll":{"count":8,"precisionRecall":{"success":{"recall":1,"precision":1}}},"porksiumai":{"count":2,"precisionRecall":{"success":{"recall":1,"precision":1}}},"saltyfishfriedrice":{"count":2,"precisionRecall":{"success":{"recall":1,"precision":1}}},"scallopsiumai":{"count":1,"precisionRecall":{"success":{"recall":1,"precision":1}}},"fishcongee":{"count":10,"precisionRecall":{"success":{"recall":1,"precision":1}}},"shrimpchips":{"count":10,"precisionRecall":{"success":{"recall":1,"precision":1}}},"shrimpfriedrice":{"count":6,"precisionRecall":{"success":{"recall":1,"precision":1}}},"steamedrice":{"count":10,"precisionRecall":{"success":{"recall":1,"precision":1}}},"yangchowfriedrice":{"count":9,"precisionRecall":{"success":{"recall":0.77777777777777779,"precision":0.77777777777777779}}},"bakedchasiubao":{"count":10,"precisionRecall":{"success":{"recall":1,"precision":1}}},"hotdogbun":{"count":4,"precisionRecall":{"success":{"recall":1,"precision":1}}},"lotusleaf":{"count":10,"precisionRecall":{"success":{"recall":1,"precision":1}}},"spamfriedrice":{"count":9,"precisionRecall":{"success":{"recall":0.77777777777777779,"precision":0.77777777777777779}}},"stuffedeggplant":{"count":9,"precisionRecall":{"success":{"recall":1,"precision":1}}},"rabbitbun":{"count":3,"precisionRecall":{"success":{"recall":1,"precision":1}}},"claypot":{"count":7,"precisionRecall":{"success":{"recall":1,"precision":0.875}}},"chinesesausagefriedrice":{"count":2,"precisionRecall":{"success":{"recall":1,"precision":1}}},"seafoodfriedrice":{"count":2,"precisionRecall":{"success":{"recall":1,"precision":1}}},"shrimproll":{"count":8,"precisionRecall":{"success":{"recall":1,"precision":1}}},"chickenfeet":{"count":7,"precisionRecall":{"success":{"recall":1,"precision":1}}},"mangopudding":{"count":11,"precisionRecall":{"success":{"recall":1,"precision":1}}},"mooncake":{"count":10,"precisionRecall":{"success":{"recall":1,"precision":1}}},"guabao":{"count":4,"precisionRecall":{"success":{"recall":1,"precision":1}}},"custardbun":{"count":9,"precisionRecall":{"success":{"recall":1,"precision":1}}},"salmonriceroll":{"count":5,"precisionRecall":{"success":{"recall":1,"precision":1}}},"shanghaisoupdumpling":{"count":10,"precisionRecall":{"success":{"recall":1,"precision":1}}},"wontonnoodlesoup":{"count":8,"precisionRecall":{"success":{"recall":1,"precision":1}}},"porkshrimpiumai":{"count":12,"precisionRecall":{"success":{"recall":1,"precision":1}}},"shrimpriceroll":{"count":9,"precisionRecall":{"success":{"recall":1,"precision":1}}},"chaozhoufunguo":{"count":4,"precisionRecall":{"success":{"recall":1,"precision":1}}},"stickyricecake":{"count":6,"precisionRecall":{"success":{"recall":1,"precision":1}}},"chasiurice":{"count":10,"precisionRecall":{"success":{"recall":1,"precision":1}}},"pigletbun":{"count":12,"precisionRecall":{"success":{"recall":1,"precision":1}}},"bakedlavabun":{"count":8,"precisionRecall":{"success":{"recall":1,"precision":1}}},"greentea":{"count":5,"precisionRecall":{"success":{"recall":1,"precision":1}}},"sausageroll":{"count":7,"precisionRecall":{"success":{"recall":1,"precision":1}}},"puertea":{"count":5,"precisionRecall":{"success":{"recall":1,"precision":1}}},"wintermelontea":{"count":9,"precisionRecall":{"success":{"recall":1,"precision":1}}},"spinachandshrimpdumpling":{"count":10,"precisionRecall":{"success":{"recall":1,"precision":1}}},"springroll":{"count":8,"precisionRecall":{"success":{"recall":1,"precision":1}}}},"accuracy":0.99244712990936557}},"createdDate":"2022-10-30T23:57:49Z","id":"6f85e4ed-9231-4822-a374-7f9c01eb1a0b","dataURL":"file:\/\/\/Users\/philipchu\/dev\/github\/dimsumml\/train\/","dataSourceID":"384A0C1F-BB47-4B79-9D3C-A28B7D418D05","dataResult":{"itemsCount":702,"createdDate":"2022-10-30T23:57:49Z","dataURL":"file:\/\/\/Users\/philipchu\/dev\/github\/dimsumml\/train\/","dataSourceID":"384A0C1F-BB47-4B79-9D3C-A28B7D418D05","classesCount":92,"dataAnalysis":{"summary":{"sampleCount":702,"classCount":92,"canUseValidation":1},"issues":[{"description":"92 classes found, including pigletbun, porkshrimpiumai, shrimpdumpling","severity":"debug"},{"description":"702 images found, automatically creating validation set","severity":"good"},{"description":"Smallest class is \"scallopsiumai\" with 1 images","severity":"debug"},{"description":"Largest class is \"pigletbun\" with 14 images","severity":"debug"}],"classifierAnalysis":{"labelStats":{"friedeggtomatonoodlesoup":6,"malaycake":10,"porksungbun":9,"billionairefriedrice":1,"panfriedriceroll":4,"westlakesoup":10,"chasiupuff":8,"steamedegg":10,"sweetpotatosoup":8,"friedshrimp":10,"porkbelly":9,"tofuskinroll":10,"chasiubao":10,"deepfrieddumpling":9,"mushroomsiumai":3,"redoilwonton":3,"jellyfishsalad":5,"seaweedsalad":5,"tofupudding":9,"friedwonton":10,"fishsiumai":2,"pineapplebun":7,"saltandpeppersquid":5,"friedfishball":8,"sugarcaneshrimp":7,"shrimpsiumai":3,"hklemonicetea":8,"jasminetea":10,"tarodumpling":10,"shrimpdumpling":12,"mochi":4,"hkeggtart":10,"flakyskinbakedchasiubao":10,"currypuff":10,"chinesebroccoli":10,"stuffedtofu":5,"preservedeggporkcongee":10,"vegetablefriedrice":2,"chivedumpling":10,"curryfishball":7,"turnipcake":10,"meatball":10,"vietnamesespringroll":7,"singaporenoodles":10,"portugueseeggtart":10,"saltedfishmincedporkclaypotrice":6,"beefriceroll":9,"mangogreentea":3,"sesameball":10,"chasiufriedrice":8,"oolongtea":10,"eggfriedrice":2,"chasiuriceroll":8,"porksiumai":3,"saltyfishfriedrice":2,"scallopsiumai":1,"fishcongee":10,"shrimpchips":10,"shrimpfriedrice":6,"steamedrice":10,"yangchowfriedrice":9,"bakedchasiubao":10,"hotdogbun":5,"lotusleaf":10,"spamfriedrice":9,"stuffedeggplant":10,"rabbitbun":3,"claypot":7,"chinesesausagefriedrice":4,"seafoodfriedrice":2,"shrimproll":8,"chickenfeet":7,"mangopudding":11,"mooncake":10,"guabao":4,"custardbun":10,"salmonriceroll":5,"shanghaisoupdumpling":10,"wontonnoodlesoup":8,"porkshrimpiumai":13,"shrimpriceroll":10,"chaozhoufunguo":5,"stickyricecake":7,"chasiurice":10,"pigletbun":14,"bakedlavabun":10,"greentea":5,"sausageroll":7,"puertea":5,"wintermelontea":10,"spinachandshrimpdumpling":10,"springroll":10}}}},"analysedDataType":"none"},"previewType":"imageClassifier","modifiedDate":"2022-10-30T23:59:27Z","validationEvaluationEntity":{"id":"2174615b-c38c-441f-84d0-8bcb487b2a34","createdDate":"2022-10-30T23:57:49Z","dataResult":{"createdDate":"2022-10-30T23:57:49Z"},"analysedDataType":"auto","evaluationResult":{"imageClassifier":{"confusionMatrix":[{"expected":"bakedlavabun","actual":"bakedlavabun","count":2},{"expected":"beefriceroll","actual":"beefriceroll","count":1},{"expected":"chaozhoufunguo","actual":"chaozhoufunguo","count":1},{"expected":"porkshrimpiumai","actual":"chasiubao","count":1},{"expected":"tofupudding","actual":"chasiubao","count":1},{"expected":"chasiufriedrice","actual":"chasiufriedrice","count":1},{"expected":"chinesesausagefriedrice","actual":"chinesesausagefriedrice","count":2},{"expected":"shrimpdumpling","actual":"custardbun","count":1},{"expected":"bakedchasiubao","actual":"deepfrieddumpling","count":1},{"expected":"deepfrieddumpling","actual":"deepfrieddumpling","count":2},{"expected":"shrimpfriedrice","actual":"eggfriedrice","count":1},{"expected":"friedeggtomatonoodlesoup","actual":"friedeggtomatonoodlesoup","count":1},{"expected":"friedshrimp","actual":"friedshrimp","count":1},{"expected":"hkeggtart","actual":"hkeggtart","count":2},{"expected":"hotdogbun","actual":"hotdogbun","count":1},{"expected":"jellyfishsalad","actual":"jellyfishsalad","count":1},{"expected":"malaycake","actual":"malaycake","count":1},{"expected":"portugueseeggtart","actual":"malaycake","count":1},{"expected":"wintermelontea","actual":"mangogreentea","count":1},{"expected":"meatball","actual":"meatball","count":2},{"expected":"bakedchasiubao","actual":"mochi","count":2},{"expected":"pigletbun","actual":"pigletbun","count":2},{"expected":"shrimpsiumai","actual":"porkshrimpiumai","count":1},{"expected":"porksiumai","actual":"porksiumai","count":1},{"expected":"sesameball","actual":"sesameball","count":1},{"expected":"redoilwonton","actual":"shrimpriceroll","count":1},{"expected":"bakedchasiubao","actual":"springroll","count":1},{"expected":"springroll","actual":"springroll","count":1},{"expected":"shrimpdumpling","actual":"stickyricecake","count":1},{"expected":"stuffedeggplant","actual":"stuffedeggplant","count":1},{"expected":"sugarcaneshrimp","actual":"sugarcaneshrimp","count":1},{"expected":"tofupudding","actual":"tofupudding","count":1},{"expected":"wintermelontea","actual":"wintermelontea","count":1}],"statsByLabel":{"shrimpriceroll":{"count":1,"precisionRecall":{"success":{"recall":0,"precision":0}}},"porkshrimpiumai":{"count":1,"precisionRecall":{"success":{"recall":0,"precision":0}}},"friedshrimp":{"count":1,"precisionRecall":{"success":{"recall":1,"precision":1}}},"wintermelontea":{"count":1,"precisionRecall":{"success":{"recall":1,"precision":0.5}}},"mangogreentea":{"count":1,"precisionRecall":{"success":{"recall":0,"precision":0}}},"shrimpdumpling":{"count":0,"precisionRecall":{"success":{"recall":0,"precision":0}}},"shrimpsiumai":{"count":0,"precisionRecall":{"success":{"recall":0,"precision":0}}},"stuffedeggplant":{"count":1,"precisionRecall":{"success":{"recall":1,"precision":1}}},"portugueseeggtart":{"count":0,"precisionRecall":{"success":{"recall":0,"precision":0}}},"chinesesausagefriedrice":{"count":2,"precisionRecall":{"success":{"recall":1,"precision":1}}},"tofupudding":{"count":1,"precisionRecall":{"success":{"recall":1,"precision":0.5}}},"sugarcaneshrimp":{"count":1,"precisionRecall":{"success":{"recall":1,"precision":1}}},"beefriceroll":{"count":1,"precisionRecall":{"success":{"recall":1,"precision":1}}},"chasiubao":{"count":2,"precisionRecall":{"success":{"recall":0,"precision":0}}},"sesameball":{"count":1,"precisionRecall":{"success":{"recall":1,"precision":1}}},"chaozhoufunguo":{"count":1,"precisionRecall":{"success":{"recall":1,"precision":1}}},"custardbun":{"count":1,"precisionRecall":{"success":{"recall":0,"precision":0}}},"chasiufriedrice":{"count":1,"precisionRecall":{"success":{"recall":1,"precision":1}}},"springroll":{"count":2,"precisionRecall":{"success":{"recall":0.5,"precision":1}}},"stickyricecake":{"count":1,"precisionRecall":{"success":{"recall":0,"precision":0}}},"porksiumai":{"count":1,"precisionRecall":{"success":{"recall":1,"precision":1}}},"hkeggtart":{"count":2,"precisionRecall":{"success":{"recall":1,"precision":1}}},"eggfriedrice":{"count":1,"precisionRecall":{"success":{"recall":0,"precision":0}}},"redoilwonton":{"count":0,"precisionRecall":{"success":{"recall":0,"precision":0}}},"mochi":{"count":2,"precisionRecall":{"success":{"recall":0,"precision":0}}},"meatball":{"count":2,"precisionRecall":{"success":{"recall":1,"precision":1}}},"shrimpfriedrice":{"count":0,"precisionRecall":{"success":{"recall":0,"precision":0}}},"hotdogbun":{"count":1,"precisionRecall":{"success":{"recall":1,"precision":1}}},"friedeggtomatonoodlesoup":{"count":1,"precisionRecall":{"success":{"recall":1,"precision":1}}},"bakedchasiubao":{"count":0,"precisionRecall":{"success":{"recall":0,"precision":0}}},"deepfrieddumpling":{"count":3,"precisionRecall":{"success":{"recall":0.66666666666666663,"precision":1}}},"pigletbun":{"count":2,"precisionRecall":{"success":{"recall":1,"precision":1}}},"malaycake":{"count":2,"precisionRecall":{"success":{"recall":0.5,"precision":1}}},"jellyfishsalad":{"count":1,"precisionRecall":{"success":{"recall":1,"precision":1}}},"bakedlavabun":{"count":2,"precisionRecall":{"success":{"recall":1,"precision":1}}}},"accuracy":0.67500000000000004}}},"evaluationEntities":[]},"activityEntities":["trainingStarted",[{"id":"3D9B2610-901B-4DE4-BD61-227A98BA6CBE","title":"Training Started","createdDate":"2022-10-30T23:57:59Z","event":"trainingStarted","subtitle":"25 iterations"}],"trainingFinished",[{"id":"782299FB-A034-4FEC-ADF4-117DDBDE28AD","title":"Training Completed","createdDate":"2022-10-30T23:59:27Z","event":"trainingFinished","subtitle":"25 iterations"}],"experimentCreated",[{"id":"866E6E6B-569E-4EE9-A149-7A25D3834C20","title":"Model Source Created","createdDate":"2022-10-30T23:57:49Z","event":"experimentCreated","subtitle":"DimSumClassifier 1"}],"trainingDataAdded",[{"id":"9404798F-A525-438D-9DCF-5CF23C715009","title":"Training Data Added","createdDate":"2022-10-30T23:57:54Z","event":"trainingDataAdded","subtitle":"train"}]],"evaluationState":"uninitialized","title":"DimSumClassifier 1","evaluationEntity":{"id":"ff8288ee-b560-49d4-8d91-f152c6ae5351","analysedDataType":"none","dataResult":{}},"snapshotRole":{"withoutSnapshots":0},"contentDataResult":{"createdDate":"2022-10-30T23:57:49Z"},"modifiedDate":"2022-10-30T23:59:27Z","preferredFilename":"DimSumClassifier 1"}